Metadata-Version: 1.0
Name: lgt-data
Version: 0.8
Summary: LGT data builds
Home-page: UNKNOWN
Author: UNKNOWN
Author-email: alexander.grin1997@gmail.com
License: UNKNOWN
Platform: UNKNOWN
